[
  {
    "itemName": "create_team",
    "imageName": "ballhelp_create_team.png",
    "roiFront": "529,487,220,58",
    "roiBack": "529,487,220,58",
    "method": "Template matching",
    "threshold": 0.8,
    "description": "创建队伍"
  },
  {
    "itemName": "battle_emo",
    "imageName": "ballhelp_battle_emo.png",
    "roiFront": "41,409,31,36",
    "roiBack": "41,409,31,36",
    "method": "Template matching",
    "threshold": 0.8,
    "description": "description"
  },
  {
    "itemName": "plate_ensure",
    "imageName": "ballhelp_plate_ensure.png",
    "roiFront": "670,403,178,60",
    "roiBack": "670,403,178,60",
    "method": "Template matching",
    "threshold": 0.8,
    "description": "description"
  }
]